{"stem":"20,000","instances":[{"docId":"sections_02-publishing-and-library-costs-the-book","docUri":"sections\/02-publishing-and-library-costs-the-book.html","score":3,"contexts":[{"form":"20,000","context":"...over 10,000 1 book in 10 sells over <mark>20,000<\/mark>","weight":1,"pos":975,"fid":"main"},{"form":"20,000","context":"There are about <mark>20,000<\/mark> periodicals, including newspapers, issued in the United...","weight":1,"pos":1169,"fid":"main"},{"form":"20,000","context":"<mark>20,000<\/mark>","weight":1,"pos":1541,"fid":"main"}]},{"docId":"sections_11-cost-levels-and-applications-of-microcopying-and-projection-reading","docUri":"sections\/11-cost-levels-and-applications-of-microcopying-and-projection-reading.html","score":2,"contexts":[{"form":"20,000","context":"...to copy its internal records. The operators photograph <mark>20,000<\/mark> statements, 7” x 10”, per day. Speed...","weight":1,"pos":4812,"fid":"main"},{"form":"20,000","context":"...(black on white) card. The costs run from $<mark>20,000<\/mark> to $30,000 per million cards.","weight":1,"pos":13422,"fid":"main"}]},{"docId":"sections_05-the-typescript-book-or-memorandum-reproduction-techniques","docUri":"sections\/05-the-typescript-book-or-memorandum-reproduction-techniques.html","score":2,"contexts":[{"form":"20,000","context":"...page, quoted in units of 57 pages, or <mark>20,000<\/mark> words, including cheap binding)","weight":1,"pos":10455,"fid":"main"},{"form":"20,000","context":"...“Edwards type” and the “author type” figures for <mark>20,000<\/mark> words is $18.00; the price of the...","weight":1,"pos":10510,"fid":"main"}]},{"docId":"sections_14-conclusion","docUri":"sections\/14-conclusion.html","score":1,"contexts":[{"form":"20,000","context":"<mark>20,000<\/mark>","weight":1,"pos":843,"fid":"main"}]},{"docId":"sections_09-binding-vertical-filing-and-film-storage","docUri":"sections\/09-binding-vertical-filing-and-film-storage.html","score":1,"contexts":[{"form":"20,000","context":"...a newspaper like the New York Times (approximately <mark>20,000<\/mark> pages, twenty-four volumes) amounts to $54.00, and...","weight":1,"pos":1135,"fid":"main"}]},{"docId":"sections_07-books-containing-characters-not-in-the-roman-alphabet-tabular-matter-diagrams-and-illustrations","docUri":"sections\/07-books-containing-characters-not-in-the-roman-alphabet-tabular-matter-diagrams-and-illustrations.html","score":1,"contexts":[{"form":"20,000","context":"...a water roller. The average plate runs about <mark>20,000<\/mark> impressions, but a run of 30,000 or...","weight":1,"pos":3285,"fid":"main"}]}]}