{"stem":"crerar","instances":[{"docId":"sections_02-publishing-and-library-costs-the-book","docUri":"sections\/02-publishing-and-library-costs-the-book.html","score":1,"contexts":[{"form":"Crerar","context":"...the New York Public Library, or the John <mark>Crerar<\/mark> Library.","weight":1,"pos":1571,"fid":"main"}]},{"docId":"sections_08-a-study-of-paper-permanence","docUri":"sections\/08-a-study-of-paper-permanence.html","score":1,"contexts":[{"form":"Crerar","context":"John <mark>Crerar<\/mark> Library, Chicago, Illinois","weight":1,"pos":3979,"fid":"main"}]}]}