{"stem":"england","instances":[{"docId":"sections_04-the-typescript-book-or-memorandum-typescript","docUri":"sections\/04-the-typescript-book-or-memorandum-typescript.html","score":2,"contexts":[{"form":"England","context":"...by Dutch types which were used widely in <mark>England<\/mark> when he started his work. As D....","weight":1,"pos":1015,"fid":"main"},{"form":"England","context":"...by Dutch types which were used widely in <mark>England<\/mark> when he started his work. As D....","weight":1,"pos":1037,"fid":"main"}]},{"docId":"sections_11-cost-levels-and-applications-of-microcopying-and-projection-reading","docUri":"sections\/11-cost-levels-and-applications-of-microcopying-and-projection-reading.html","score":1,"contexts":[{"form":"England","context":"...copying two million pages of books printed in <mark>England<\/mark> before 1640—a project that would bring to...","weight":1,"pos":4986,"fid":"main"}]},{"docId":"sections_03-printed-books","docUri":"sections\/03-printed-books.html","score":1,"contexts":[{"form":"England","context":"...Company, 1–4 Red Lion Passage, Fleet Street, London, <mark>England<\/mark>, manufactures a “stripping paper.” It resembles Kodalith...","weight":1,"pos":8898,"fid":"fn:n9"}]}]}