{"stem":"gift","instances":[{"docId":"sections_14-conclusion","docUri":"sections\/14-conclusion.html","score":1,"contexts":[{"form":"gift","context":"...will perform in deciding whether to shelve the <mark>gift<\/mark> or put it in the wastebasket.","weight":1,"pos":3795,"fid":"main"}]},{"docId":"sections_02-publishing-and-library-costs-the-book","docUri":"sections\/02-publishing-and-library-costs-the-book.html","score":1,"contexts":[{"form":"gift","context":"...may be six times the value of his <mark>gift<\/mark>. That this housing cost cannot be dismissed...","weight":1,"pos":2096,"fid":"main"}]}]}