{"stem":"heavili","instances":[{"docId":"sections_04-the-typescript-book-or-memorandum-typescript","docUri":"sections\/04-the-typescript-book-or-memorandum-typescript.html","score":4,"contexts":[{"form":"heavily","context":"...typed with a lightly-inked ribbon but with a <mark>heavily<\/mark> touch.","weight":1,"pos":3385,"fid":"main"},{"form":"heavily","context":"This paragraph was typed with a <mark>heavily<\/mark>-inked ribbon and with a heavy touch. The...","weight":1,"pos":3408,"fid":"main"},{"form":"heavily","context":"This paragraph was typed with a <mark>heavily<\/mark>-inked ribbon but with a lighter more even...","weight":1,"pos":3420,"fid":"main"},{"form":"heavily","context":"This paragraph was typed with a <mark>heavily<\/mark>-inked ribbon and an uneven touch.","weight":1,"pos":3429,"fid":"main"}]},{"docId":"sections_07-books-containing-characters-not-in-the-roman-alphabet-tabular-matter-diagrams-and-illustrations","docUri":"sections\/07-books-containing-characters-not-in-the-roman-alphabet-tabular-matter-diagrams-and-illustrations.html","score":1,"contexts":[{"form":"heavily","context":"...parts. This permits the ink to lie more <mark>heavily<\/mark> in the parts of the plate that...","weight":1,"pos":2518,"fid":"main"}]},{"docId":"sections_08-a-study-of-paper-permanence","docUri":"sections\/08-a-study-of-paper-permanence.html","score":1,"contexts":[{"form":"heavily","context":"...line of development, however; its interests have been <mark>heavily<\/mark> vested in the existing trade practices. Recently...","weight":1,"pos":573,"fid":"main"}]}]}