{"stem":"layman","instances":[{"docId":"sections_08-a-study-of-paper-permanence","docUri":"sections\/08-a-study-of-paper-permanence.html","score":3,"contexts":[{"form":"layman","context":"...be interpreted? The paper technologists quickly draw the <mark>layman<\/mark> beyond his depth in the discussion, but...","weight":1,"pos":2353,"fid":"main"},{"form":"layman’s","context":"...but as supplementary information offered subject to the <mark>layman’s<\/mark> qualms as to its accuracy.","weight":1,"pos":3479,"fid":"main"},{"form":"layman","context":"...and even though the technician soon draws the <mark>layman<\/mark> beyond his depth in the discussion of...","weight":1,"pos":4083,"fid":"main"}]}]}