{"stem":"leav","instances":[{"docId":"sections_05-the-typescript-book-or-memorandum-reproduction-techniques","docUri":"sections\/05-the-typescript-book-or-memorandum-reproduction-techniques.html","score":10,"contexts":[{"form":"leaving","context":"...ef cotton. The excess fluid is wiped off, <mark>leaving<\/mark> a thin coating on the surface. The...","weight":1,"pos":2744,"fid":"main"},{"form":"leaves","context":"<mark>leaves<\/mark>","weight":1,"pos":6748,"fid":"main"},{"form":"leaves","context":"<mark>leaves<\/mark>","weight":1,"pos":6768,"fid":"main"},{"form":"leaving","context":"...in column width not greater than 2 1\/8”, <mark>leaving<\/mark> 1\/2” between columns. Such a column will...","weight":1,"pos":6946,"fid":"main"},{"form":"leaving","context":"...of it is allotted to the composition cost, <mark>leaving<\/mark> $302.50 to pay for the running costs....","weight":1,"pos":8884,"fid":"main"},{"form":"Leaving","context":"<mark>Leaving<\/mark> wide margins and typing in a single...","weight":1,"pos":8914,"fid":"main"},{"form":"leaving","context":"...of it is allotted to the composition cost, <mark>leaving<\/mark> $302.50 to pay for the running costs....","weight":1,"pos":9033,"fid":"main"},{"form":"leaving","context":"...of it must be allotted to typescript composition, <mark>leaving<\/mark> $302.50 to pay for the photo-offset work...","weight":1,"pos":9666,"fid":"main"},{"form":"Leaving","context":"...words on each 6” x 9 1\/2” page. <mark>Leaving<\/mark> wide margins and typing in a single...","weight":1,"pos":9688,"fid":"main"},{"form":"leaving","context":"...size, must pass through a reduction of 45%, <mark>leaving<\/mark> them 55% of full size. The page...","weight":1,"pos":10134,"fid":"main"}]},{"docId":"sections_03-printed-books","docUri":"sections\/03-printed-books.html","score":8,"contexts":[{"form":"leave","context":"...hammers and welded the bolts. They resolved to <mark>leave<\/mark> means neither of ingress nor egress to...","weight":1,"pos":858,"fid":"figure_01"},{"form":"leave","context":"...hammers and welded the bolts. They resolved to <mark>leave<\/mark> means neither of ingress nor egress to...","weight":1,"pos":1010,"fid":"figure_01"},{"form":"leave","context":"...only a portion of a form or to <mark>leave<\/mark> part of a signature unprinted. Printing economy...","weight":1,"pos":2509,"fid":"main"},{"form":"leave","context":"...hammers and welded the bolts. They resolved to <mark>leave<\/mark> means neither of ingress nor egress to...","weight":1,"pos":2778,"fid":"figure_04"},{"form":"leave","context":"...hammers and welded the bolts. They resolved to <mark>leave<\/mark> means neither of ingress nor egress to...","weight":1,"pos":2951,"fid":"figure_04"},{"form":"leaves","context":"...ink from the rays of the light, but <mark>leaves<\/mark> the other part intact. Thus a stencil...","weight":1,"pos":8105,"fid":"main"},{"form":"leave","context":"...expect to receive proofs of a 300-page book, <mark>leave<\/mark> them on the desk for a week,...","weight":1,"pos":8778,"fid":"fn:n7"},{"form":"leaving","context":"...coloring matter. The soluble parts are washed away, <mark>leaving<\/mark> the negative copy of the original as...","weight":1,"pos":9533,"fid":"fn:16"}]},{"docId":"sections_07-books-containing-characters-not-in-the-roman-alphabet-tabular-matter-diagrams-and-illustrations","docUri":"sections\/07-books-containing-characters-not-in-the-roman-alphabet-tabular-matter-diagrams-and-illustrations.html","score":6,"contexts":[{"form":"leave","context":"...away the exposed parts of the plate and <mark>leave<\/mark> the pro∥ tected parts as a raised...","weight":1,"pos":1589,"fid":"main"},{"form":"leaving","context":"...the darkest greys the black dots rum together, <mark>leaving<\/mark> small white dots between them.","weight":1,"pos":1832,"fid":"main"},{"form":"leaves","context":"...is rapidly dried with heat. The rapid drying <mark>leaves<\/mark> the gelatin in a state of strain....","weight":1,"pos":2382,"fid":"main"},{"form":"leave","context":"...bichromated gelatin; the dark parts of the negative <mark>leave<\/mark> the gelatin untanned. When the plate is...","weight":1,"pos":2428,"fid":"main"},{"form":"leaves","context":"...the picture that are to be light, and <mark>leaves<\/mark> it soft in those parts of the...","weight":1,"pos":2930,"fid":"main"},{"form":"leaves","context":"...and alcohol solution removes the unaffected bichromate and <mark>leaves<\/mark> a positive image. A second baking toughens...","weight":1,"pos":3249,"fid":"main"}]},{"docId":"sections_14-conclusion","docUri":"sections\/14-conclusion.html","score":4,"contexts":[{"form":"leaves","context":"...out of date almost as soon as it <mark>leaves<\/mark> the typist’s hands. Even at this writing,...","weight":1,"pos":44,"fid":"main"},{"form":"leave","context":"...and distributing their cost between authors and buyers <mark>leave<\/mark> a large margin of risk. While they...","weight":1,"pos":3872,"fid":"main"},{"form":"leave","context":"...those of professional scholars and research libraries, will <mark>leave<\/mark> the great decisions to the play of...","weight":1,"pos":4634,"fid":"main"},{"form":"leave","context":"...in the course of practical life would still <mark>leave<\/mark> a great gap in the documentation. Are...","weight":1,"pos":4651,"fid":"main"}]},{"docId":"sections_06-blueprinting-photostating-and-allied-techniques","docUri":"sections\/06-blueprinting-photostating-and-allied-techniques.html","score":3,"contexts":[{"form":"leaving","context":"...the press it would print a black background, <mark>leaving<\/mark> the letters white, for the bare metal...","weight":1,"pos":137,"fid":"main"},{"form":"leaves","context":"...two kinds of apparatus: a standard equipment, which <mark>leaves<\/mark> it to the operator to shift the...","weight":1,"pos":3259,"fid":"main"},{"form":"leaving","context":"...a small camera to make film copies, while <mark>leaving<\/mark> the work of enlarging to be done...","weight":1,"pos":3625,"fid":"main"}]},{"docId":"sections_11-cost-levels-and-applications-of-microcopying-and-projection-reading","docUri":"sections\/11-cost-levels-and-applications-of-microcopying-and-projection-reading.html","score":3,"contexts":[{"form":"leaving","context":"...column the full length of the film but <mark>leaving<\/mark> space on the film for more than...","weight":1,"pos":3865,"fid":"main"},{"form":"leaving","context":"...is copied on a continuous strip of film, <mark>leaving<\/mark> spaces between for cutting. When all the...","weight":1,"pos":5973,"fid":"main"},{"form":"leaves","context":"...met. First, the binding of the papers often <mark>leaves<\/mark> the inner column obscured because of the...","weight":1,"pos":12727,"fid":"main"}]},{"docId":"sections_12-photographic-and-projecting-apparatus","docUri":"sections\/12-photographic-and-projecting-apparatus.html","score":2,"contexts":[{"form":"leave","context":"But the photographer can take <mark>leave<\/mark> of the catalogue and its prices when...","weight":1,"pos":2262,"fid":"main"},{"form":"leave","context":"...make the exposure of pre-determined duration. This will <mark>leave<\/mark> both hands free for the manipulation of...","weight":1,"pos":3479,"fid":"main"}]},{"docId":"sections_04-the-typescript-book-or-memorandum-typescript","docUri":"sections\/04-the-typescript-book-or-memorandum-typescript.html","score":1,"contexts":[{"form":"leaving","context":"...The typewriter, moreover, does not produce justified lines, <mark>leaving<\/mark> an uneven right-hand margin so unusual in...","weight":1,"pos":1050,"fid":"main"}]},{"docId":"sections_09-binding-vertical-filing-and-film-storage","docUri":"sections\/09-binding-vertical-filing-and-film-storage.html","score":1,"contexts":[{"form":"leaves","context":"...of corners (round or square), treatment of fly <mark>leaves<\/mark> (tipped or turned), stamping or lettering, and...","weight":1,"pos":1054,"fid":"main"}]},{"docId":"sections_02-publishing-and-library-costs-the-book","docUri":"sections\/02-publishing-and-library-costs-the-book.html","score":1,"contexts":[{"form":"leaving","context":"...was donated, take up 39% of the money, <mark>leaving<\/mark> 61% for book purchase and administration. If...","weight":1,"pos":2025,"fid":"main"}]},{"docId":"sections_08-a-study-of-paper-permanence","docUri":"sections\/08-a-study-of-paper-permanence.html","score":1,"contexts":[{"form":"leave","context":"...the small editions which do not threaten to <mark>leave<\/mark> their makers with a great bulk of...","weight":1,"pos":3257,"fid":"main"}]}]}