{"stem":"ludwig","instances":[{"docId":"sections_12-photographic-and-projecting-apparatus","docUri":"sections\/12-photographic-and-projecting-apparatus.html","score":8,"contexts":[{"form":"Ludwig","context":"<mark>Ludwig<\/mark> camera, made to order (used at Yale...","weight":1,"pos":105,"fid":"main"},{"form":"Ludwig","context":"...and Folmer Graflex cameras have automatic focusing; the <mark>Ludwig<\/mark> camera has no automatic features. Sometimes the...","weight":1,"pos":572,"fid":"main"},{"form":"Ludwig","context":"<mark>Ludwig<\/mark> Camera","weight":1,"pos":939,"fid":"main"},{"form":"Ludwig","context":"Frederick <mark>Ludwig<\/mark> Yale University New Haven, Conn.","weight":1,"pos":942,"fid":"main"},{"form":"Ludwig","context":"The <mark>Ludwig<\/mark> Camera","weight":1,"pos":2780,"fid":"the-ludwig-camera"},{"form":"Ludwig","context":"...The photographer of Yale University Library, Mr. Frederick <mark>Ludwig<\/mark>, has designed a camera based on the...","weight":1,"pos":2787,"fid":"main"},{"form":"Ludwig","context":"Mr. <mark>Ludwig<\/mark> has built a number of these cameras...","weight":1,"pos":2880,"fid":"main"},{"form":"Ludwig","context":"...accurate but also more troublesome than with the <mark>Ludwig<\/mark> or Leica cameras.","weight":1,"pos":3134,"fid":"main"}]},{"docId":"sections_11-cost-levels-and-applications-of-microcopying-and-projection-reading","docUri":"sections\/11-cost-levels-and-applications-of-microcopying-and-projection-reading.html","score":1,"contexts":[{"form":"Ludwig","context":"...“double frame” used in the Leica, Contax, and <mark>Ludwig<\/mark> cameras exposes an area 1” x 1...","weight":1,"pos":9343,"fid":"main"}]}]}