{"stem":"mark","instances":[{"docId":"sections_03-printed-books","docUri":"sections\/03-printed-books.html","score":7,"contexts":[{"form":"markedly","context":"...such a degree that speed of reading is <mark>markedly<\/mark> decreased.” In the June 1929 issue on...","weight":1,"pos":1518,"fid":"figure_02"},{"form":"mark","context":"...the size of the edition passes the 600 <mark>mark<\/mark>. The costs per page as here quoted...","weight":1,"pos":5322,"fid":"main"},{"form":"marks","context":"...A stone surface was covered with the greasy <mark>marks<\/mark> of a lithographic pencil, then moistened and...","weight":1,"pos":5607,"fid":"main"},{"form":"marks","context":"...inked. The ink would adhere to the pencil <mark>marks<\/mark>, avoid the moistened spaces, and transfer to...","weight":1,"pos":5616,"fid":"main"},{"form":"marks","context":"...each page. The scholar takes one page and <mark>marks<\/mark> in it all the words to be...","weight":1,"pos":7373,"fid":"main"},{"form":"marked","context":"...typist then takes one loose-leaf for each word <mark>marked<\/mark> by the scholar, types the marked work...","weight":1,"pos":7383,"fid":"main"},{"form":"marked","context":"...each word marked by the scholar, types the <mark>marked<\/mark> work at the top of the leaf...","weight":1,"pos":7386,"fid":"main"}]},{"docId":"sections_05-the-typescript-book-or-memorandum-reproduction-techniques","docUri":"sections\/05-the-typescript-book-or-memorandum-reproduction-techniques.html","score":7,"contexts":[{"form":"mark","context":"...reductions in price start- ing at the 10,000 <mark>mark<\/mark>. It is a 204 highly absorbent paper...","weight":1,"pos":1274,"fid":"main"},{"form":"mark","context":"...in legibility begins after the 100 or 150 <mark>mark<\/mark> is reached. This diminution in contrast may...","weight":1,"pos":1640,"fid":"main"},{"form":"marked","context":"...cocaine, the local anesthetic action being, however, more <mark>marked<\/mark>. This was confirmed in human eyes by...","weight":1,"pos":9421,"fid":"main"},{"form":"marked","context":"<mark>marked<\/mark> at the same time. Although it causes...","weight":1,"pos":9454,"fid":"main"},{"form":"marked","context":"...to the local anesthetic action, but it causes <mark>marked<\/mark> irritation and swelling and for this reason...","weight":1,"pos":9515,"fid":"main"},{"form":"marked","context":"...printers often provide such sheets. With paper so <mark>marked<\/mark>, and with the right ratchet and ribbon...","weight":1,"pos":10855,"fid":"main"},{"form":"marked","context":"...can be typed directly on a large sheet <mark>marked<\/mark> off into two columns or upon a...","weight":1,"pos":10885,"fid":"main"}]},{"docId":"sections_08-a-study-of-paper-permanence","docUri":"sections\/08-a-study-of-paper-permanence.html","score":4,"contexts":[{"form":"mark","context":"Under normal trade conditions the trade <mark>mark<\/mark>-ups and discounts should permit price variations in...","weight":1,"pos":2911,"fid":"main"},{"form":"mark","context":"The distributor’s <mark>mark<\/mark>-up would range from $1.60 in the one-case...","weight":1,"pos":2947,"fid":"main"},{"form":"mark","context":"...$.50 to $.95 in carload lots. The printer’s <mark>mark<\/mark>-up should be anything from 10% to 25%...","weight":1,"pos":2961,"fid":"main"},{"form":"mark","context":"...25% of what he pays the dealer. These <mark>mark<\/mark>-ups do not constitute an excessive charge for...","weight":1,"pos":2966,"fid":"main"}]},{"docId":"sections_11-cost-levels-and-applications-of-microcopying-and-projection-reading","docUri":"sections\/11-cost-levels-and-applications-of-microcopying-and-projection-reading.html","score":3,"contexts":[{"form":"marked","context":"...of steps, photographic and in printing, that have <mark>marked<\/mark> the transmission of the two clippings at...","weight":1,"pos":996,"fid":"main"},{"form":"marked","context":"...copy, legible with a reading glass, would offer <mark>marked<\/mark> convenience in storage and filing. Equipment for...","weight":1,"pos":10116,"fid":"main"},{"form":"marking","context":"...the holdings indicated on the film copy by <mark>marking<\/mark> the Library of Congress card whenever the...","weight":1,"pos":13310,"fid":"main"}]},{"docId":"sections_14-conclusion","docUri":"sections\/14-conclusion.html","score":3,"contexts":[{"form":"mark","context":"...The running costs really begin after the 100 <mark>mark<\/mark> is passed. In photo-offset quotations the minimum...","weight":1,"pos":499,"fid":"main"},{"form":"marked","context":"...remain to be worked out; they will show <mark>marked<\/mark> differences from the accountancy of publishing. They...","weight":1,"pos":3671,"fid":"main"},{"form":"mark","context":"...and the creation of a National Archives administration <mark>mark<\/mark> a new day in the treatment of...","weight":1,"pos":5199,"fid":"main"}]},{"docId":"sections_02-publishing-and-library-costs-the-book","docUri":"sections\/02-publishing-and-library-costs-the-book.html","score":3,"contexts":[{"form":"markedly","context":"...elements of printing cost do not decrease so <mark>markedly<\/mark> as the quantity increases, the same principle...","weight":1,"pos":527,"fid":"main"},{"form":"mark","context":"...after sales have passed well beyond the 1000 <mark>mark<\/mark>.","weight":1,"pos":922,"fid":"main"},{"form":"marked","context":"Thus, everything points to the <mark>marked<\/mark> difference between scholarly and commercial publishing economy,...","weight":1,"pos":1062,"fid":"main"}]},{"docId":"sections_06-blueprinting-photostating-and-allied-techniques","docUri":"sections\/06-blueprinting-photostating-and-allied-techniques.html","score":1,"contexts":[{"form":"mark","context":"...positives meet each other close to the twenty-five <mark>mark<\/mark>.","weight":1,"pos":4460,"fid":"main"}]},{"docId":"sections_04-the-typescript-book-or-memorandum-typescript","docUri":"sections\/04-the-typescript-book-or-memorandum-typescript.html","score":1,"contexts":[{"form":"marking","context":"...that follow the ability to use italics in <mark>marking<\/mark> passages for emphasis is an example. As...","weight":1,"pos":1622,"fid":"main"}]},{"docId":"sections_12-photographic-and-projecting-apparatus","docUri":"sections\/12-photographic-and-projecting-apparatus.html","score":1,"contexts":[{"form":"marked","context":"...collecting and organizing of material should have a <mark>marked<\/mark> effect on intellectual standards in research. ∣📄...","weight":1,"pos":4994,"fid":"main"}]}]}