{"stem":"nch","instances":[{"docId":"sections_05-the-typescript-book-or-memorandum-reproduction-techniques","docUri":"sections\/05-the-typescript-book-or-memorandum-reproduction-techniques.html","score":3,"contexts":[{"form":"NCH","context":"Eee A C Tore COOC; H, <mark>NCH<\/mark>, Hcoocé \\ | a ars C—— C——...","weight":1,"pos":9337,"fid":"main"},{"form":"NCH","context":"c C—— C_ COOCH,CH = CH, <mark>NCH<\/mark>, HCooc ) | ge —","weight":1,"pos":9392,"fid":"main"},{"form":"NCH","context":"...H \\ C Ceemeern cooc ¢ | ie <mark>NCH<\/mark>, acooc€ | pet sl eaelee eae eee...","weight":1,"pos":9477,"fid":"main"}]}]}