{"stem":"notebook","instances":[{"docId":"sections_09-binding-vertical-filing-and-film-storage","docUri":"sections\/09-binding-vertical-filing-and-film-storage.html","score":2,"contexts":[{"form":"notebook","context":"Spiral binding is a form of <mark>notebook<\/mark> binding that is becoming increasingly popular for...","weight":1,"pos":348,"fid":"main"},{"form":"notebook","context":"...together by rings as in the simplest loose-leaf <mark>notebook<\/mark> style, but instead of two or three...","weight":1,"pos":382,"fid":"main"}]},{"docId":"sections_04-the-typescript-book-or-memorandum-typescript","docUri":"sections\/04-the-typescript-book-or-memorandum-typescript.html","score":1,"contexts":[{"form":"notebooks","context":"...low. Bond paper, filing cabinets, folders, and loose-leaf <mark>notebooks<\/mark> have been standardized to sizes ∥ that...","weight":1,"pos":226,"fid":"main"}]}]}