{"stem":"resort","instances":[{"docId":"sections_11-cost-levels-and-applications-of-microcopying-and-projection-reading","docUri":"sections\/11-cost-levels-and-applications-of-microcopying-and-projection-reading.html","score":2,"contexts":[{"form":"resort","context":"∣📄 p.131 <mark>resort<\/mark> to low processing costs may entail a...","weight":1,"pos":4481,"fid":"main"},{"form":"resort","context":"...Administration money for wages made it necessary to <mark>resort<\/mark> to typing.","weight":1,"pos":13275,"fid":"main"}]},{"docId":"sections_03-printed-books","docUri":"sections\/03-printed-books.html","score":2,"contexts":[{"form":"resort","context":"...size on the other. True it is that <mark>resort<\/mark> to compact type faces and light leading...","weight":1,"pos":3151,"fid":"main"},{"form":"resorted","context":"...are elsewhere discussed. If ordinary linotype composition were <mark>resorted<\/mark> to with this process, no saving would...","weight":1,"pos":5937,"fid":"main"}]},{"docId":"sections_04-the-typescript-book-or-memorandum-typescript","docUri":"sections\/04-the-typescript-book-or-memorandum-typescript.html","score":1,"contexts":[{"form":"resorting","context":"By using the Varityper, and by <mark>resorting<\/mark> to two typings, an even right-hand margin...","weight":1,"pos":1828,"fid":"main"}]},{"docId":"sections_07-books-containing-characters-not-in-the-roman-alphabet-tabular-matter-diagrams-and-illustrations","docUri":"sections\/07-books-containing-characters-not-in-the-roman-alphabet-tabular-matter-diagrams-and-illustrations.html","score":1,"contexts":[{"form":"resort","context":"...that will show different shades of grey requires <mark>resort<\/mark> to an optical illusion.","weight":1,"pos":1758,"fid":"main"}]}]}