{"stem":"testifi","instances":[{"docId":"sections_11-cost-levels-and-applications-of-microcopying-and-projection-reading","docUri":"sections\/11-cost-levels-and-applications-of-microcopying-and-projection-reading.html","score":2,"contexts":[{"form":"testify","context":"...is not yet clear, but the observer must <mark>testify<\/mark> to the clear ∣📄 p.151 intelligence with...","weight":1,"pos":10852,"fid":"main"},{"form":"testify","context":"...old files. The experts of the Recordak Corporation <mark>testify<\/mark> that even these pages can be handled...","weight":1,"pos":12820,"fid":"main"}]}]}