{"stem":"vast","instances":[{"docId":"sections_14-conclusion","docUri":"sections\/14-conclusion.html","score":8,"contexts":[{"form":"vast","context":"...material desired by 2000 paying customers. But a <mark>vast<\/mark> amount of material for scholarly use and...","weight":1,"pos":234,"fid":"main"},{"form":"vast","context":"...way to the professional in research, and the <mark>vast<\/mark> corps of teachers in the secondary schools...","weight":1,"pos":4094,"fid":"main"},{"form":"vast","context":"...an organized unit, as if it were a <mark>vast<\/mark> and well-designed book. Collections of documents in...","weight":1,"pos":4192,"fid":"main"},{"form":"vast","context":"...The world of paper is a world of <mark>vast<\/mark> dimensions. Primarily, it is not a world...","weight":1,"pos":4481,"fid":"main"},{"form":"vast","context":"...some kinds of old manuscripts. But there are <mark>vast<\/mark> domains of records which our libraries cannot...","weight":1,"pos":4579,"fid":"main"},{"form":"vast","context":"...The field of original record is so <mark>vast<\/mark> that the conclusion must be self-evident; only...","weight":1,"pos":4700,"fid":"main"},{"form":"vast","context":"...creation, preservation, and collection of research material in <mark>vast<\/mark> quantities will embarrass rather than aid scholarship,...","weight":1,"pos":4864,"fid":"main"},{"form":"vast","context":"...archives, business documents, or family papers, is a <mark>vast<\/mark> task in which a large element of...","weight":1,"pos":5818,"fid":"main"}]},{"docId":"sections_11-cost-levels-and-applications-of-microcopying-and-projection-reading","docUri":"sections\/11-cost-levels-and-applications-of-microcopying-and-projection-reading.html","score":2,"contexts":[{"form":"vast","context":"...Watson Davis of Science Service has devoted a <mark>vast<\/mark> amount of intensive thought and planning. The...","weight":1,"pos":7580,"fid":"main"},{"form":"vast","context":"...archive of our civilization. Each unit in the <mark>vast<\/mark> library system can perform a task that...","weight":1,"pos":14132,"fid":"main"}]}]}