{"stem":"wider","instances":[{"docId":"sections_09-binding-vertical-filing-and-film-storage","docUri":"sections\/09-binding-vertical-filing-and-film-storage.html","score":1,"contexts":[{"form":"wider","context":"...is adapted only to very short strips, no <mark>wider<\/mark> than a card used in a vertical...","weight":1,"pos":1226,"fid":"main"}]},{"docId":"sections_03-printed-books","docUri":"sections\/03-printed-books.html","score":1,"contexts":[{"form":"wider","context":"...and Century Expanded, are used at a slightly <mark>wider<\/mark> set; while others, like Bruce Old Style,...","weight":1,"pos":2107,"fid":"main"}]},{"docId":"sections_05-the-typescript-book-or-memorandum-reproduction-techniques","docUri":"sections\/05-the-typescript-book-or-memorandum-reproduction-techniques.html","score":1,"contexts":[{"form":"wider","context":"...the type size is simply turned over to <mark>wider<\/mark> margins. But here two possibilities intervene: the...","weight":1,"pos":5017,"fid":"main"}]}]}